{"identifier":{"url":"doc:\/\/com.squareup.MobilePaymentsSDKAPI\/documentation\/MobilePaymentsSDKAPI","interfaceLanguage":"swift"},"kind":"symbol","schemaVersion":{"patch":0,"minor":3,"major":0},"topicSections":[{"identifiers":["doc:\/\/com.squareup.MobilePaymentsSDKAPI\/documentation\/MobilePaymentsSDKAPI\/AdditionalPaymentMethods","doc:\/\/com.squareup.MobilePaymentsSDKAPI\/documentation\/MobilePaymentsSDKAPI\/CardInputMethods","doc:\/\/com.squareup.MobilePaymentsSDKAPI\/documentation\/MobilePaymentsSDKAPI\/KeyedCardPaymentSource","doc:\/\/com.squareup.MobilePaymentsSDKAPI\/documentation\/MobilePaymentsSDKAPI\/Money","doc:\/\/com.squareup.MobilePaymentsSDKAPI\/documentation\/MobilePaymentsSDKAPI\/PaymentParameters","doc:\/\/com.squareup.MobilePaymentsSDKAPI\/documentation\/MobilePaymentsSDKAPI\/PromptParameters","doc:\/\/com.squareup.MobilePaymentsSDKAPI\/documentation\/MobilePaymentsSDKAPI\/TapToPayPaymentSource"],"generated":true,"anchor":"Classes","title":"Classes"},{"identifiers":["doc:\/\/com.squareup.MobilePaymentsSDKAPI\/documentation\/MobilePaymentsSDKAPI\/AdditionalPaymentMethod","doc:\/\/com.squareup.MobilePaymentsSDKAPI\/documentation\/MobilePaymentsSDKAPI\/AuthorizationManager","doc:\/\/com.squareup.MobilePaymentsSDKAPI\/documentation\/MobilePaymentsSDKAPI\/AuthorizationStateObserver","doc:\/\/com.squareup.MobilePaymentsSDKAPI\/documentation\/MobilePaymentsSDKAPI\/AvailableCardInputMethodsObserver","doc:\/\/com.squareup.MobilePaymentsSDKAPI\/documentation\/MobilePaymentsSDKAPI\/Card","doc:\/\/com.squareup.MobilePaymentsSDKAPI\/documentation\/MobilePaymentsSDKAPI\/CardHandle","doc:\/\/com.squareup.MobilePaymentsSDKAPI\/documentation\/MobilePaymentsSDKAPI\/CardPaymentDetails","doc:\/\/com.squareup.MobilePaymentsSDKAPI\/documentation\/MobilePaymentsSDKAPI\/Location","doc:\/\/com.squareup.MobilePaymentsSDKAPI\/documentation\/MobilePaymentsSDKAPI\/MoneyAmount","doc:\/\/com.squareup.MobilePaymentsSDKAPI\/documentation\/MobilePaymentsSDKAPI\/OfflineCard","doc:\/\/com.squareup.MobilePaymentsSDKAPI\/documentation\/MobilePaymentsSDKAPI\/OfflineCardPaymentDetails","doc:\/\/com.squareup.MobilePaymentsSDKAPI\/documentation\/MobilePaymentsSDKAPI\/OfflinePayment","doc:\/\/com.squareup.MobilePaymentsSDKAPI\/documentation\/MobilePaymentsSDKAPI\/OfflinePaymentQueue","doc:\/\/com.squareup.MobilePaymentsSDKAPI\/documentation\/MobilePaymentsSDKAPI\/OnlinePayment","doc:\/\/com.squareup.MobilePaymentsSDKAPI\/documentation\/MobilePaymentsSDKAPI\/PairingHandle","doc:\/\/com.squareup.MobilePaymentsSDKAPI\/documentation\/MobilePaymentsSDKAPI\/Payment","doc:\/\/com.squareup.MobilePaymentsSDKAPI\/documentation\/MobilePaymentsSDKAPI\/PaymentHandle","doc:\/\/com.squareup.MobilePaymentsSDKAPI\/documentation\/MobilePaymentsSDKAPI\/PaymentManager","doc:\/\/com.squareup.MobilePaymentsSDKAPI\/documentation\/MobilePaymentsSDKAPI\/PaymentManagerDelegate","doc:\/\/com.squareup.MobilePaymentsSDKAPI\/documentation\/MobilePaymentsSDKAPI\/PaymentSettings","doc:\/\/com.squareup.MobilePaymentsSDKAPI\/documentation\/MobilePaymentsSDKAPI\/PaymentSource","doc:\/\/com.squareup.MobilePaymentsSDKAPI\/documentation\/MobilePaymentsSDKAPI\/ReadCardInfoManager","doc:\/\/com.squareup.MobilePaymentsSDKAPI\/documentation\/MobilePaymentsSDKAPI\/ReadCardInfoObserver","doc:\/\/com.squareup.MobilePaymentsSDKAPI\/documentation\/MobilePaymentsSDKAPI\/ReaderBatteryStatus","doc:\/\/com.squareup.MobilePaymentsSDKAPI\/documentation\/MobilePaymentsSDKAPI\/ReaderConnectionFailureInfo","doc:\/\/com.squareup.MobilePaymentsSDKAPI\/documentation\/MobilePaymentsSDKAPI\/ReaderConnectionInfo","doc:\/\/com.squareup.MobilePaymentsSDKAPI\/documentation\/MobilePaymentsSDKAPI\/ReaderFirmwareInfo","doc:\/\/com.squareup.MobilePaymentsSDKAPI\/documentation\/MobilePaymentsSDKAPI\/ReaderInfo","doc:\/\/com.squareup.MobilePaymentsSDKAPI\/documentation\/MobilePaymentsSDKAPI\/ReaderManager","doc:\/\/com.squareup.MobilePaymentsSDKAPI\/documentation\/MobilePaymentsSDKAPI\/ReaderObserver","doc:\/\/com.squareup.MobilePaymentsSDKAPI\/documentation\/MobilePaymentsSDKAPI\/ReaderPairingDelegate","doc:\/\/com.squareup.MobilePaymentsSDKAPI\/documentation\/MobilePaymentsSDKAPI\/ReaderStatusInfo","doc:\/\/com.squareup.MobilePaymentsSDKAPI\/documentation\/MobilePaymentsSDKAPI\/ReaderUnavailableReasonInfo","doc:\/\/com.squareup.MobilePaymentsSDKAPI\/documentation\/MobilePaymentsSDKAPI\/SDKManager","doc:\/\/com.squareup.MobilePaymentsSDKAPI\/documentation\/MobilePaymentsSDKAPI\/SDKSettings","doc:\/\/com.squareup.MobilePaymentsSDKAPI\/documentation\/MobilePaymentsSDKAPI\/SettingsManager","doc:\/\/com.squareup.MobilePaymentsSDKAPI\/documentation\/MobilePaymentsSDKAPI\/TapToPaySettings"],"generated":true,"anchor":"Protocols","title":"Protocols"},{"identifiers":["doc:\/\/com.squareup.MobilePaymentsSDKAPI\/documentation\/MobilePaymentsSDKAPI\/AdditionalPaymentMethodType","doc:\/\/com.squareup.MobilePaymentsSDKAPI\/documentation\/MobilePaymentsSDKAPI\/AuthorizationError","doc:\/\/com.squareup.MobilePaymentsSDKAPI\/documentation\/MobilePaymentsSDKAPI\/AuthorizationState","doc:\/\/com.squareup.MobilePaymentsSDKAPI\/documentation\/MobilePaymentsSDKAPI\/CardBrand","doc:\/\/com.squareup.MobilePaymentsSDKAPI\/documentation\/MobilePaymentsSDKAPI\/CardCoBrand","doc:\/\/com.squareup.MobilePaymentsSDKAPI\/documentation\/MobilePaymentsSDKAPI\/CardEntryMethod","doc:\/\/com.squareup.MobilePaymentsSDKAPI\/documentation\/MobilePaymentsSDKAPI\/CardInsertionStatus","doc:\/\/com.squareup.MobilePaymentsSDKAPI\/documentation\/MobilePaymentsSDKAPI\/CardPaymentStatus","doc:\/\/com.squareup.MobilePaymentsSDKAPI\/documentation\/MobilePaymentsSDKAPI\/Currency","doc:\/\/com.squareup.MobilePaymentsSDKAPI\/documentation\/MobilePaymentsSDKAPI\/DelayAction","doc:\/\/com.squareup.MobilePaymentsSDKAPI\/documentation\/MobilePaymentsSDKAPI\/Environment","doc:\/\/com.squareup.MobilePaymentsSDKAPI\/documentation\/MobilePaymentsSDKAPI\/OfflinePaymentQueueError","doc:\/\/com.squareup.MobilePaymentsSDKAPI\/documentation\/MobilePaymentsSDKAPI\/OfflineStatus","doc:\/\/com.squareup.MobilePaymentsSDKAPI\/documentation\/MobilePaymentsSDKAPI\/PaymentError","doc:\/\/com.squareup.MobilePaymentsSDKAPI\/documentation\/MobilePaymentsSDKAPI\/PaymentStatus","doc:\/\/com.squareup.MobilePaymentsSDKAPI\/documentation\/MobilePaymentsSDKAPI\/ProcessingMode","doc:\/\/com.squareup.MobilePaymentsSDKAPI\/documentation\/MobilePaymentsSDKAPI\/PromptMode","doc:\/\/com.squareup.MobilePaymentsSDKAPI\/documentation\/MobilePaymentsSDKAPI\/ReadCardInfoError","doc:\/\/com.squareup.MobilePaymentsSDKAPI\/documentation\/MobilePaymentsSDKAPI\/ReaderBatteryLevel","doc:\/\/com.squareup.MobilePaymentsSDKAPI\/documentation\/MobilePaymentsSDKAPI\/ReaderChange","doc:\/\/com.squareup.MobilePaymentsSDKAPI\/documentation\/MobilePaymentsSDKAPI\/ReaderConnectionFailureReason","doc:\/\/com.squareup.MobilePaymentsSDKAPI\/documentation\/MobilePaymentsSDKAPI\/ReaderConnectionFailureRecoverySuggestion","doc:\/\/com.squareup.MobilePaymentsSDKAPI\/documentation\/MobilePaymentsSDKAPI\/ReaderConnectionState","doc:\/\/com.squareup.MobilePaymentsSDKAPI\/documentation\/MobilePaymentsSDKAPI\/ReaderFirmwareUpdateError","doc:\/\/com.squareup.MobilePaymentsSDKAPI\/documentation\/MobilePaymentsSDKAPI\/ReaderModel","doc:\/\/com.squareup.MobilePaymentsSDKAPI\/documentation\/MobilePaymentsSDKAPI\/ReaderPairingError","doc:\/\/com.squareup.MobilePaymentsSDKAPI\/documentation\/MobilePaymentsSDKAPI\/ReaderState","doc:\/\/com.squareup.MobilePaymentsSDKAPI\/documentation\/MobilePaymentsSDKAPI\/ReaderStatus","doc:\/\/com.squareup.MobilePaymentsSDKAPI\/documentation\/MobilePaymentsSDKAPI\/ReaderUnavailableReason","doc:\/\/com.squareup.MobilePaymentsSDKAPI\/documentation\/MobilePaymentsSDKAPI\/SourceType","doc:\/\/com.squareup.MobilePaymentsSDKAPI\/documentation\/MobilePaymentsSDKAPI\/TapToPayReaderError","doc:\/\/com.squareup.MobilePaymentsSDKAPI\/documentation\/MobilePaymentsSDKAPI\/TrackingConsentState"],"generated":true,"anchor":"Enumerations","title":"Enumerations"}],"hierarchy":{"paths":[[]]},"metadata":{"externalID":"MobilePaymentsSDKAPI","roleHeading":"Framework","role":"collection","symbolKind":"module","modules":[{"name":"MobilePaymentsSDKAPI"}],"title":"MobilePaymentsSDKAPI"},"variants":[{"paths":["\/documentation\/mobilepaymentssdkapi"],"traits":[{"interfaceLanguage":"swift"}]}],"sections":[],"references":{"doc://com.squareup.MobilePaymentsSDKAPI/documentation/MobilePaymentsSDKAPI/ReaderState":{"fragments":[{"text":"enum","kind":"keyword"},{"text":" ","kind":"text"},{"text":"ReaderState","kind":"identifier"}],"deprecated":true,"type":"topic","title":"ReaderState","abstract":[{"type":"text","text":"The reader’s state."}],"kind":"symbol","navigatorTitle":[{"text":"ReaderState","kind":"identifier"}],"url":"\/documentation\/mobilepaymentssdkapi\/readerstate","role":"symbol","identifier":"doc:\/\/com.squareup.MobilePaymentsSDKAPI\/documentation\/MobilePaymentsSDKAPI\/ReaderState"},"doc://com.squareup.MobilePaymentsSDKAPI/documentation/MobilePaymentsSDKAPI/ReaderUnavailableReasonInfo":{"identifier":"doc:\/\/com.squareup.MobilePaymentsSDKAPI\/documentation\/MobilePaymentsSDKAPI\/ReaderUnavailableReasonInfo","role":"symbol","fragments":[{"text":"protocol","kind":"keyword"},{"text":" ","kind":"text"},{"text":"ReaderUnavailableReasonInfo","kind":"identifier"}],"type":"topic","kind":"symbol","title":"ReaderUnavailableReasonInfo","navigatorTitle":[{"text":"ReaderUnavailableReasonInfo","kind":"identifier"}],"url":"\/documentation\/mobilepaymentssdkapi\/readerunavailablereasoninfo","abstract":[]},"doc://com.squareup.MobilePaymentsSDKAPI/documentation/MobilePaymentsSDKAPI/ReaderChange":{"navigatorTitle":[{"text":"ReaderChange","kind":"identifier"}],"title":"ReaderChange","type":"topic","url":"\/documentation\/mobilepaymentssdkapi\/readerchange","abstract":[{"text":"Indicates changes that can occur within a reader","type":"text"}],"role":"symbol","fragments":[{"text":"enum","kind":"keyword"},{"text":" ","kind":"text"},{"text":"ReaderChange","kind":"identifier"}],"identifier":"doc:\/\/com.squareup.MobilePaymentsSDKAPI\/documentation\/MobilePaymentsSDKAPI\/ReaderChange","kind":"symbol"},"doc://com.squareup.MobilePaymentsSDKAPI/documentation/MobilePaymentsSDKAPI/Payment":{"navigatorTitle":[{"text":"Payment","kind":"identifier"}],"identifier":"doc:\/\/com.squareup.MobilePaymentsSDKAPI\/documentation\/MobilePaymentsSDKAPI\/Payment","role":"symbol","kind":"symbol","type":"topic","url":"\/documentation\/mobilepaymentssdkapi\/payment","title":"Payment","fragments":[{"text":"protocol","kind":"keyword"},{"text":" ","kind":"text"},{"text":"Payment","kind":"identifier"}],"abstract":[{"text":"A representation of a payment. See ","type":"text"},{"isActive":true,"type":"reference","identifier":"https:\/\/developer.squareup.com\/reference\/square\/payments-api\/create-payment"},{"text":" for more information.","type":"text"}]},"doc://com.squareup.MobilePaymentsSDKAPI/documentation/MobilePaymentsSDKAPI/OfflineStatus":{"fragments":[{"kind":"keyword","text":"enum"},{"kind":"text","text":" "},{"kind":"identifier","text":"OfflineStatus"}],"url":"\/documentation\/mobilepaymentssdkapi\/offlinestatus","role":"symbol","abstract":[{"type":"text","text":"The status of an "},{"type":"codeVoice","code":"OfflinePayment"},{"type":"text","text":"."}],"title":"OfflineStatus","type":"topic","identifier":"doc:\/\/com.squareup.MobilePaymentsSDKAPI\/documentation\/MobilePaymentsSDKAPI\/OfflineStatus","kind":"symbol","navigatorTitle":[{"kind":"identifier","text":"OfflineStatus"}]},"doc://com.squareup.MobilePaymentsSDKAPI/documentation/MobilePaymentsSDKAPI/PromptMode":{"url":"\/documentation\/mobilepaymentssdkapi\/promptmode","type":"topic","abstract":[{"type":"text","text":"Mode to describe which kind of payment prompt will be used for the payment."}],"identifier":"doc:\/\/com.squareup.MobilePaymentsSDKAPI\/documentation\/MobilePaymentsSDKAPI\/PromptMode","fragments":[{"text":"enum","kind":"keyword"},{"text":" ","kind":"text"},{"text":"PromptMode","kind":"identifier"}],"title":"PromptMode","kind":"symbol","navigatorTitle":[{"text":"PromptMode","kind":"identifier"}],"role":"symbol"},"doc://com.squareup.MobilePaymentsSDKAPI/documentation/MobilePaymentsSDKAPI/ReaderModel":{"title":"ReaderModel","identifier":"doc:\/\/com.squareup.MobilePaymentsSDKAPI\/documentation\/MobilePaymentsSDKAPI\/ReaderModel","url":"\/documentation\/mobilepaymentssdkapi\/readermodel","kind":"symbol","fragments":[{"text":"enum","kind":"keyword"},{"text":" ","kind":"text"},{"text":"ReaderModel","kind":"identifier"}],"navigatorTitle":[{"text":"ReaderModel","kind":"identifier"}],"role":"symbol","type":"topic","abstract":[{"text":"The hardware model of the reader.","type":"text"}]},"doc://com.squareup.MobilePaymentsSDKAPI/documentation/MobilePaymentsSDKAPI/TapToPayReaderError":{"abstract":[{"type":"text","text":"Error conditions that arise when performing Apple Tap to Pay."}],"identifier":"doc:\/\/com.squareup.MobilePaymentsSDKAPI\/documentation\/MobilePaymentsSDKAPI\/TapToPayReaderError","url":"\/documentation\/mobilepaymentssdkapi\/taptopayreadererror","kind":"symbol","title":"TapToPayReaderError","fragments":[{"kind":"keyword","text":"enum"},{"kind":"text","text":" "},{"kind":"identifier","text":"TapToPayReaderError"}],"navigatorTitle":[{"kind":"identifier","text":"TapToPayReaderError"}],"role":"symbol","type":"topic"},"doc://com.squareup.MobilePaymentsSDKAPI/documentation/MobilePaymentsSDKAPI/ReaderConnectionFailureInfo":{"kind":"symbol","abstract":[{"text":"Provides additional information if the ","type":"text"},{"code":"ReaderConnectionState","type":"codeVoice"},{"text":" is ","type":"text"},{"code":".failedToConnect","type":"codeVoice"},{"text":".","type":"text"}],"type":"topic","navigatorTitle":[{"kind":"identifier","text":"ReaderConnectionFailureInfo"}],"url":"\/documentation\/mobilepaymentssdkapi\/readerconnectionfailureinfo","fragments":[{"kind":"keyword","text":"protocol"},{"kind":"text","text":" "},{"kind":"identifier","text":"ReaderConnectionFailureInfo"}],"role":"symbol","title":"ReaderConnectionFailureInfo","identifier":"doc:\/\/com.squareup.MobilePaymentsSDKAPI\/documentation\/MobilePaymentsSDKAPI\/ReaderConnectionFailureInfo"},"doc://com.squareup.MobilePaymentsSDKAPI/documentation/MobilePaymentsSDKAPI/ReaderPairingError":{"type":"topic","fragments":[{"text":"enum","kind":"keyword"},{"text":" ","kind":"text"},{"text":"ReaderPairingError","kind":"identifier"}],"identifier":"doc:\/\/com.squareup.MobilePaymentsSDKAPI\/documentation\/MobilePaymentsSDKAPI\/ReaderPairingError","title":"ReaderPairingError","abstract":[{"type":"text","text":"Error conditions that arise when pairing reader"}],"role":"symbol","navigatorTitle":[{"text":"ReaderPairingError","kind":"identifier"}],"kind":"symbol","url":"\/documentation\/mobilepaymentssdkapi\/readerpairingerror"},"doc://com.squareup.MobilePaymentsSDKAPI/documentation/MobilePaymentsSDKAPI/MoneyAmount":{"fragments":[{"kind":"keyword","text":"protocol"},{"kind":"text","text":" "},{"kind":"identifier","text":"MoneyAmount"}],"abstract":[{"type":"text","text":"Represents an amount of money."}],"identifier":"doc:\/\/com.squareup.MobilePaymentsSDKAPI\/documentation\/MobilePaymentsSDKAPI\/MoneyAmount","type":"topic","role":"symbol","title":"MoneyAmount","navigatorTitle":[{"kind":"identifier","text":"MoneyAmount"}],"kind":"symbol","url":"\/documentation\/mobilepaymentssdkapi\/moneyamount"},"doc://com.squareup.MobilePaymentsSDKAPI/documentation/MobilePaymentsSDKAPI/PaymentSource":{"title":"PaymentSource","abstract":[{"type":"text","text":"Base type of a source to create a payment with"}],"kind":"symbol","role":"symbol","navigatorTitle":[{"text":"PaymentSource","kind":"identifier"}],"type":"topic","identifier":"doc:\/\/com.squareup.MobilePaymentsSDKAPI\/documentation\/MobilePaymentsSDKAPI\/PaymentSource","url":"\/documentation\/mobilepaymentssdkapi\/paymentsource","fragments":[{"text":"protocol","kind":"keyword"},{"text":" ","kind":"text"},{"text":"PaymentSource","kind":"identifier"}]},"doc://com.squareup.MobilePaymentsSDKAPI/documentation/MobilePaymentsSDKAPI/PaymentHandle":{"kind":"symbol","abstract":[{"type":"text","text":"Represents an ongoing payment and provides a way to cancel the payment or enter card manually."}],"title":"PaymentHandle","url":"\/documentation\/mobilepaymentssdkapi\/paymenthandle","role":"symbol","navigatorTitle":[{"text":"PaymentHandle","kind":"identifier"}],"type":"topic","fragments":[{"text":"protocol","kind":"keyword"},{"text":" ","kind":"text"},{"text":"PaymentHandle","kind":"identifier"}],"identifier":"doc:\/\/com.squareup.MobilePaymentsSDKAPI\/documentation\/MobilePaymentsSDKAPI\/PaymentHandle"},"doc://com.squareup.MobilePaymentsSDKAPI/documentation/MobilePaymentsSDKAPI/OnlinePayment":{"type":"topic","kind":"symbol","fragments":[{"kind":"keyword","text":"protocol"},{"kind":"text","text":" "},{"kind":"identifier","text":"OnlinePayment"}],"identifier":"doc:\/\/com.squareup.MobilePaymentsSDKAPI\/documentation\/MobilePaymentsSDKAPI\/OnlinePayment","title":"OnlinePayment","role":"symbol","abstract":[{"type":"text","text":"A representation of an online payment"}],"navigatorTitle":[{"kind":"identifier","text":"OnlinePayment"}],"url":"\/documentation\/mobilepaymentssdkapi\/onlinepayment"},"doc://com.squareup.MobilePaymentsSDKAPI/documentation/MobilePaymentsSDKAPI/CardPaymentDetails":{"fragments":[{"text":"protocol","kind":"keyword"},{"text":" ","kind":"text"},{"text":"CardPaymentDetails","kind":"identifier"}],"type":"topic","navigatorTitle":[{"text":"CardPaymentDetails","kind":"identifier"}],"identifier":"doc:\/\/com.squareup.MobilePaymentsSDKAPI\/documentation\/MobilePaymentsSDKAPI\/CardPaymentDetails","kind":"symbol","abstract":[{"text":"Details about a successful card payment.","type":"text"}],"title":"CardPaymentDetails","role":"symbol","url":"\/documentation\/mobilepaymentssdkapi\/cardpaymentdetails"},"doc://com.squareup.MobilePaymentsSDKAPI/documentation/MobilePaymentsSDKAPI/SourceType":{"title":"SourceType","identifier":"doc:\/\/com.squareup.MobilePaymentsSDKAPI\/documentation\/MobilePaymentsSDKAPI\/SourceType","url":"\/documentation\/mobilepaymentssdkapi\/sourcetype","abstract":[{"type":"text","text":"The source type for the payment."}],"kind":"symbol","role":"symbol","navigatorTitle":[{"kind":"identifier","text":"SourceType"}],"fragments":[{"kind":"keyword","text":"enum"},{"kind":"text","text":" "},{"kind":"identifier","text":"SourceType"}],"type":"topic"},"doc://com.squareup.MobilePaymentsSDKAPI/documentation/MobilePaymentsSDKAPI/ReaderStatus":{"kind":"symbol","fragments":[{"text":"enum","kind":"keyword"},{"text":" ","kind":"text"},{"text":"ReaderStatus","kind":"identifier"}],"url":"\/documentation\/mobilepaymentssdkapi\/readerstatus","title":"ReaderStatus","abstract":[],"identifier":"doc:\/\/com.squareup.MobilePaymentsSDKAPI\/documentation\/MobilePaymentsSDKAPI\/ReaderStatus","role":"symbol","navigatorTitle":[{"text":"ReaderStatus","kind":"identifier"}],"type":"topic"},"doc://com.squareup.MobilePaymentsSDKAPI/documentation/MobilePaymentsSDKAPI/ReaderConnectionState":{"title":"ReaderConnectionState","identifier":"doc:\/\/com.squareup.MobilePaymentsSDKAPI\/documentation\/MobilePaymentsSDKAPI\/ReaderConnectionState","abstract":[{"text":"Indicates the current connection state of a Reader","type":"text"}],"navigatorTitle":[{"text":"ReaderConnectionState","kind":"identifier"}],"url":"\/documentation\/mobilepaymentssdkapi\/readerconnectionstate","role":"symbol","kind":"symbol","fragments":[{"kind":"keyword","text":"enum"},{"kind":"text","text":" "},{"kind":"identifier","text":"ReaderConnectionState"}],"type":"topic"},"doc://com.squareup.MobilePaymentsSDKAPI/documentation/MobilePaymentsSDKAPI/ReaderFirmwareInfo":{"navigatorTitle":[{"text":"ReaderFirmwareInfo","kind":"identifier"}],"url":"\/documentation\/mobilepaymentssdkapi\/readerfirmwareinfo","title":"ReaderFirmwareInfo","fragments":[{"text":"protocol","kind":"keyword"},{"text":" ","kind":"text"},{"text":"ReaderFirmwareInfo","kind":"identifier"}],"type":"topic","abstract":[{"text":"The firmware info of the reader","type":"text"}],"identifier":"doc:\/\/com.squareup.MobilePaymentsSDKAPI\/documentation\/MobilePaymentsSDKAPI\/ReaderFirmwareInfo","kind":"symbol","role":"symbol"},"doc://com.squareup.MobilePaymentsSDKAPI/documentation/MobilePaymentsSDKAPI/ReaderPairingDelegate":{"kind":"symbol","role":"symbol","navigatorTitle":[{"text":"ReaderPairingDelegate","kind":"identifier"}],"fragments":[{"text":"protocol","kind":"keyword"},{"text":" ","kind":"text"},{"text":"ReaderPairingDelegate","kind":"identifier"}],"url":"\/documentation\/mobilepaymentssdkapi\/readerpairingdelegate","title":"ReaderPairingDelegate","type":"topic","identifier":"doc:\/\/com.squareup.MobilePaymentsSDKAPI\/documentation\/MobilePaymentsSDKAPI\/ReaderPairingDelegate","abstract":[{"type":"text","text":"The delegate provided to a "},{"type":"codeVoice","code":"startPairing"},{"type":"text","text":" call must adopt the "},{"type":"codeVoice","code":"ReaderPairingDelegate"},{"type":"text","text":" protocol."}]},"doc://com.squareup.MobilePaymentsSDKAPI/documentation/MobilePaymentsSDKAPI/CardInsertionStatus":{"kind":"symbol","navigatorTitle":[{"text":"CardInsertionStatus","kind":"identifier"}],"identifier":"doc:\/\/com.squareup.MobilePaymentsSDKAPI\/documentation\/MobilePaymentsSDKAPI\/CardInsertionStatus","url":"\/documentation\/mobilepaymentssdkapi\/cardinsertionstatus","fragments":[{"text":"enum","kind":"keyword"},{"text":" ","kind":"text"},{"text":"CardInsertionStatus","kind":"identifier"}],"abstract":[{"type":"text","text":"The state of a card inside of a reader."}],"role":"symbol","type":"topic","title":"CardInsertionStatus"},"doc://com.squareup.MobilePaymentsSDKAPI/documentation/MobilePaymentsSDKAPI/Location":{"fragments":[{"kind":"keyword","text":"protocol"},{"kind":"text","text":" "},{"kind":"identifier","text":"Location"}],"role":"symbol","kind":"symbol","identifier":"doc:\/\/com.squareup.MobilePaymentsSDKAPI\/documentation\/MobilePaymentsSDKAPI\/Location","navigatorTitle":[{"kind":"identifier","text":"Location"}],"type":"topic","title":"Location","url":"\/documentation\/mobilepaymentssdkapi\/location","abstract":[{"type":"text","text":"Locations represent the sources of orders and fulfillments for businesses."}]},"doc://com.squareup.MobilePaymentsSDKAPI/documentation/MobilePaymentsSDKAPI/ReaderManager":{"fragments":[{"kind":"keyword","text":"protocol"},{"kind":"text","text":" "},{"kind":"identifier","text":"ReaderManager"}],"url":"\/documentation\/mobilepaymentssdkapi\/readermanager","title":"ReaderManager","kind":"symbol","abstract":[{"type":"text","text":"The "},{"type":"codeVoice","code":"ReaderManager"},{"type":"text","text":" handles interactions with Square card readers, including pairing Bluetooth readers, getting the current set of available readers, and observing changes in available readers."}],"identifier":"doc:\/\/com.squareup.MobilePaymentsSDKAPI\/documentation\/MobilePaymentsSDKAPI\/ReaderManager","type":"topic","navigatorTitle":[{"kind":"identifier","text":"ReaderManager"}],"role":"symbol"},"doc://com.squareup.MobilePaymentsSDKAPI/documentation/MobilePaymentsSDKAPI/KeyedCardPaymentSource":{"url":"\/documentation\/mobilepaymentssdkapi\/keyedcardpaymentsource","role":"symbol","navigatorTitle":[{"text":"KeyedCardPaymentSource","kind":"identifier"}],"type":"topic","identifier":"doc:\/\/com.squareup.MobilePaymentsSDKAPI\/documentation\/MobilePaymentsSDKAPI\/KeyedCardPaymentSource","kind":"symbol","fragments":[{"text":"class","kind":"keyword"},{"text":" ","kind":"text"},{"text":"KeyedCardPaymentSource","kind":"identifier"}],"title":"KeyedCardPaymentSource","abstract":[{"text":"Instructs the SDK to begin a Keyed Payment","type":"text"}]},"doc://com.squareup.MobilePaymentsSDKAPI/documentation/MobilePaymentsSDKAPI/Money":{"type":"topic","role":"symbol","fragments":[{"kind":"keyword","text":"class"},{"kind":"text","text":" "},{"kind":"identifier","text":"Money"}],"navigatorTitle":[{"kind":"identifier","text":"Money"}],"url":"\/documentation\/mobilepaymentssdkapi\/money","title":"Money","kind":"symbol","abstract":[{"text":"Represents an amount of money.","type":"text"}],"identifier":"doc:\/\/com.squareup.MobilePaymentsSDKAPI\/documentation\/MobilePaymentsSDKAPI\/Money"},"doc://com.squareup.MobilePaymentsSDKAPI/documentation/MobilePaymentsSDKAPI/ProcessingMode":{"kind":"symbol","role":"symbol","navigatorTitle":[{"text":"ProcessingMode","kind":"identifier"}],"title":"ProcessingMode","url":"\/documentation\/mobilepaymentssdkapi\/processingmode","type":"topic","identifier":"doc:\/\/com.squareup.MobilePaymentsSDKAPI\/documentation\/MobilePaymentsSDKAPI\/ProcessingMode","abstract":[{"type":"text","text":"Defines the modes for processing payments offline or online."}],"fragments":[{"text":"enum","kind":"keyword"},{"text":" ","kind":"text"},{"text":"ProcessingMode","kind":"identifier"}]},"doc://com.squareup.MobilePaymentsSDKAPI/documentation/MobilePaymentsSDKAPI/ReaderFirmwareUpdateError":{"abstract":[{"text":"Error conditions that arise when pairing reader","type":"text"}],"role":"symbol","title":"ReaderFirmwareUpdateError","url":"\/documentation\/mobilepaymentssdkapi\/readerfirmwareupdateerror","kind":"symbol","type":"topic","navigatorTitle":[{"kind":"identifier","text":"ReaderFirmwareUpdateError"}],"identifier":"doc:\/\/com.squareup.MobilePaymentsSDKAPI\/documentation\/MobilePaymentsSDKAPI\/ReaderFirmwareUpdateError","fragments":[{"kind":"keyword","text":"enum"},{"kind":"text","text":" "},{"kind":"identifier","text":"ReaderFirmwareUpdateError"}]},"doc://com.squareup.MobilePaymentsSDKAPI/documentation/MobilePaymentsSDKAPI/ReaderInfo":{"abstract":[{"type":"text","text":"Information about an individual card reader"}],"title":"ReaderInfo","navigatorTitle":[{"kind":"identifier","text":"ReaderInfo"}],"type":"topic","kind":"symbol","role":"symbol","fragments":[{"kind":"keyword","text":"protocol"},{"kind":"text","text":" "},{"kind":"identifier","text":"ReaderInfo"}],"identifier":"doc:\/\/com.squareup.MobilePaymentsSDKAPI\/documentation\/MobilePaymentsSDKAPI\/ReaderInfo","url":"\/documentation\/mobilepaymentssdkapi\/readerinfo"},"doc://com.squareup.MobilePaymentsSDKAPI/documentation/MobilePaymentsSDKAPI/OfflinePaymentQueueError":{"type":"topic","title":"OfflinePaymentQueueError","url":"\/documentation\/mobilepaymentssdkapi\/offlinepaymentqueueerror","role":"symbol","navigatorTitle":[{"text":"OfflinePaymentQueueError","kind":"identifier"}],"kind":"symbol","fragments":[{"text":"enum","kind":"keyword"},{"text":" ","kind":"text"},{"text":"OfflinePaymentQueueError","kind":"identifier"}],"abstract":[{"type":"text","text":"Errors relating to the Offline Payment Queue failing."}],"identifier":"doc:\/\/com.squareup.MobilePaymentsSDKAPI\/documentation\/MobilePaymentsSDKAPI\/OfflinePaymentQueueError"},"doc://com.squareup.MobilePaymentsSDKAPI/documentation/MobilePaymentsSDKAPI/ReaderBatteryStatus":{"title":"ReaderBatteryStatus","identifier":"doc:\/\/com.squareup.MobilePaymentsSDKAPI\/documentation\/MobilePaymentsSDKAPI\/ReaderBatteryStatus","url":"\/documentation\/mobilepaymentssdkapi\/readerbatterystatus","kind":"symbol","fragments":[{"kind":"keyword","text":"protocol"},{"kind":"text","text":" "},{"kind":"identifier","text":"ReaderBatteryStatus"}],"navigatorTitle":[{"kind":"identifier","text":"ReaderBatteryStatus"}],"role":"symbol","type":"topic","abstract":[{"type":"text","text":"The current battery status of a reader."}]},"doc://com.squareup.MobilePaymentsSDKAPI/documentation/MobilePaymentsSDKAPI/Card":{"url":"\/documentation\/mobilepaymentssdkapi\/card","fragments":[{"kind":"keyword","text":"protocol"},{"kind":"text","text":" "},{"kind":"identifier","text":"Card"}],"abstract":[{"text":"The card’s non-confidential details.","type":"text"}],"kind":"symbol","navigatorTitle":[{"kind":"identifier","text":"Card"}],"identifier":"doc:\/\/com.squareup.MobilePaymentsSDKAPI\/documentation\/MobilePaymentsSDKAPI\/Card","title":"Card","role":"symbol","type":"topic"},"doc://com.squareup.MobilePaymentsSDKAPI/documentation/MobilePaymentsSDKAPI/OfflineCardPaymentDetails":{"type":"topic","role":"symbol","identifier":"doc:\/\/com.squareup.MobilePaymentsSDKAPI\/documentation\/MobilePaymentsSDKAPI\/OfflineCardPaymentDetails","title":"OfflineCardPaymentDetails","url":"\/documentation\/mobilepaymentssdkapi\/offlinecardpaymentdetails","fragments":[{"text":"protocol","kind":"keyword"},{"text":" ","kind":"text"},{"text":"OfflineCardPaymentDetails","kind":"identifier"}],"kind":"symbol","navigatorTitle":[{"text":"OfflineCardPaymentDetails","kind":"identifier"}],"abstract":[{"type":"text","text":"Details about a card payment taken offline."}]},"doc://com.squareup.MobilePaymentsSDKAPI/documentation/MobilePaymentsSDKAPI/CardBrand":{"kind":"symbol","role":"symbol","identifier":"doc:\/\/com.squareup.MobilePaymentsSDKAPI\/documentation\/MobilePaymentsSDKAPI\/CardBrand","title":"CardBrand","fragments":[{"kind":"keyword","text":"enum"},{"kind":"text","text":" "},{"kind":"identifier","text":"CardBrand"}],"abstract":[{"text":"The card’s brand (such as VISA).","type":"text"}],"url":"\/documentation\/mobilepaymentssdkapi\/cardbrand","navigatorTitle":[{"kind":"identifier","text":"CardBrand"}],"type":"topic"},"doc://com.squareup.MobilePaymentsSDKAPI/documentation/MobilePaymentsSDKAPI/AuthorizationManager":{"navigatorTitle":[{"text":"AuthorizationManager","kind":"identifier"}],"abstract":[{"text":"Manages Square Seller account authorization.","type":"text"}],"kind":"symbol","title":"AuthorizationManager","role":"symbol","fragments":[{"text":"protocol","kind":"keyword"},{"text":" ","kind":"text"},{"text":"AuthorizationManager","kind":"identifier"}],"type":"topic","url":"\/documentation\/mobilepaymentssdkapi\/authorizationmanager","identifier":"doc:\/\/com.squareup.MobilePaymentsSDKAPI\/documentation\/MobilePaymentsSDKAPI\/AuthorizationManager"},"doc://com.squareup.MobilePaymentsSDKAPI/documentation/MobilePaymentsSDKAPI/CardCoBrand":{"url":"\/documentation\/mobilepaymentssdkapi\/cardcobrand","fragments":[{"text":"enum","kind":"keyword"},{"text":" ","kind":"text"},{"text":"CardCoBrand","kind":"identifier"}],"navigatorTitle":[{"text":"CardCoBrand","kind":"identifier"}],"kind":"symbol","role":"symbol","abstract":[{"type":"text","text":"The card’s cobrand (such as Afterpay)."}],"identifier":"doc:\/\/com.squareup.MobilePaymentsSDKAPI\/documentation\/MobilePaymentsSDKAPI\/CardCoBrand","title":"CardCoBrand","type":"topic"},"doc://com.squareup.MobilePaymentsSDKAPI/documentation/MobilePaymentsSDKAPI/AuthorizationState":{"fragments":[{"kind":"keyword","text":"enum"},{"kind":"text","text":" "},{"kind":"identifier","text":"AuthorizationState"}],"identifier":"doc:\/\/com.squareup.MobilePaymentsSDKAPI\/documentation\/MobilePaymentsSDKAPI\/AuthorizationState","title":"AuthorizationState","url":"\/documentation\/mobilepaymentssdkapi\/authorizationstate","kind":"symbol","type":"topic","role":"symbol","abstract":[{"type":"text","text":"The current state of the SDKs authorization"}],"navigatorTitle":[{"kind":"identifier","text":"AuthorizationState"}]},"doc://com.squareup.MobilePaymentsSDKAPI/documentation/MobilePaymentsSDKAPI/PaymentError":{"identifier":"doc:\/\/com.squareup.MobilePaymentsSDKAPI\/documentation\/MobilePaymentsSDKAPI\/PaymentError","fragments":[{"text":"enum","kind":"keyword"},{"kind":"text","text":" "},{"text":"PaymentError","kind":"identifier"}],"title":"PaymentError","abstract":[{"text":"Errors relating to a payment failing.","type":"text"}],"role":"symbol","type":"topic","url":"\/documentation\/mobilepaymentssdkapi\/paymenterror","navigatorTitle":[{"text":"PaymentError","kind":"identifier"}],"kind":"symbol"},"doc://com.squareup.MobilePaymentsSDKAPI/documentation/MobilePaymentsSDKAPI/CardHandle":{"type":"topic","kind":"symbol","fragments":[{"kind":"keyword","text":"protocol"},{"kind":"text","text":" "},{"kind":"identifier","text":"CardHandle"}],"navigatorTitle":[{"kind":"identifier","text":"CardHandle"}],"role":"symbol","url":"\/documentation\/mobilepaymentssdkapi\/cardhandle","identifier":"doc:\/\/com.squareup.MobilePaymentsSDKAPI\/documentation\/MobilePaymentsSDKAPI\/CardHandle","abstract":[{"text":"A handle for a card.","type":"text"}],"title":"CardHandle"},"doc://com.squareup.MobilePaymentsSDKAPI/documentation/MobilePaymentsSDKAPI/ReadCardInfoObserver":{"url":"\/documentation\/mobilepaymentssdkapi\/readcardinfoobserver","abstract":[],"role":"symbol","fragments":[{"kind":"keyword","text":"protocol"},{"kind":"text","text":" "},{"kind":"identifier","text":"ReadCardInfoObserver"}],"navigatorTitle":[{"kind":"identifier","text":"ReadCardInfoObserver"}],"identifier":"doc:\/\/com.squareup.MobilePaymentsSDKAPI\/documentation\/MobilePaymentsSDKAPI\/ReadCardInfoObserver","type":"topic","title":"ReadCardInfoObserver","kind":"symbol"},"https://developer.squareup.com/reference/square/payments-api/create-payment":{"title":"Payments API","url":"https:\/\/developer.squareup.com\/reference\/square\/payments-api\/create-payment","identifier":"https:\/\/developer.squareup.com\/reference\/square\/payments-api\/create-payment","titleInlineContent":[{"type":"text","text":"Payments API"}],"type":"link"},"doc://com.squareup.MobilePaymentsSDKAPI/documentation/MobilePaymentsSDKAPI/OfflineCard":{"fragments":[{"text":"protocol","kind":"keyword"},{"text":" ","kind":"text"},{"text":"OfflineCard","kind":"identifier"}],"abstract":[{"type":"text","text":"The card’s non-confidential details."}],"url":"\/documentation\/mobilepaymentssdkapi\/offlinecard","kind":"symbol","identifier":"doc:\/\/com.squareup.MobilePaymentsSDKAPI\/documentation\/MobilePaymentsSDKAPI\/OfflineCard","role":"symbol","navigatorTitle":[{"text":"OfflineCard","kind":"identifier"}],"type":"topic","title":"OfflineCard"},"doc://com.squareup.MobilePaymentsSDKAPI/documentation/MobilePaymentsSDKAPI/Environment":{"title":"Environment","role":"symbol","abstract":[{"type":"text","text":"The environment the SDK has been initialized in."},{"type":"text","text":" "},{"type":"text","text":"This value indicates the environment of the SDK based on the Square application ID used during SDK initialization - "},{"code":".production","type":"codeVoice"},{"type":"text","text":" for a production ID and "},{"code":".sandbox","type":"codeVoice"},{"type":"text","text":" for a sandbox ID."}],"navigatorTitle":[{"text":"Environment","kind":"identifier"}],"url":"\/documentation\/mobilepaymentssdkapi\/environment","type":"topic","identifier":"doc:\/\/com.squareup.MobilePaymentsSDKAPI\/documentation\/MobilePaymentsSDKAPI\/Environment","kind":"symbol","fragments":[{"text":"enum","kind":"keyword"},{"text":" ","kind":"text"},{"text":"Environment","kind":"identifier"}]},"doc://com.squareup.MobilePaymentsSDKAPI/documentation/MobilePaymentsSDKAPI/PaymentManagerDelegate":{"title":"PaymentManagerDelegate","kind":"symbol","role":"symbol","abstract":[{"text":"The delegate provided to a ","type":"text"},{"code":"startPayment","type":"codeVoice"},{"text":" call must adopt the ","type":"text"},{"code":"PaymentManagerDelegate","type":"codeVoice"},{"text":" protocol","type":"text"}],"url":"\/documentation\/mobilepaymentssdkapi\/paymentmanagerdelegate","identifier":"doc:\/\/com.squareup.MobilePaymentsSDKAPI\/documentation\/MobilePaymentsSDKAPI\/PaymentManagerDelegate","navigatorTitle":[{"kind":"identifier","text":"PaymentManagerDelegate"}],"type":"topic","fragments":[{"kind":"keyword","text":"protocol"},{"kind":"text","text":" "},{"kind":"identifier","text":"PaymentManagerDelegate"}]},"doc://com.squareup.MobilePaymentsSDKAPI/documentation/MobilePaymentsSDKAPI/ReaderBatteryLevel":{"type":"topic","fragments":[{"kind":"keyword","text":"enum"},{"kind":"text","text":" "},{"kind":"identifier","text":"ReaderBatteryLevel"}],"abstract":[{"type":"text","text":"A coarse representation of the reader’s battery level."}],"title":"ReaderBatteryLevel","url":"\/documentation\/mobilepaymentssdkapi\/readerbatterylevel","role":"symbol","identifier":"doc:\/\/com.squareup.MobilePaymentsSDKAPI\/documentation\/MobilePaymentsSDKAPI\/ReaderBatteryLevel","navigatorTitle":[{"kind":"identifier","text":"ReaderBatteryLevel"}],"kind":"symbol"},"doc://com.squareup.MobilePaymentsSDKAPI/documentation/MobilePaymentsSDKAPI/AdditionalPaymentMethodType":{"url":"\/documentation\/mobilepaymentssdkapi\/additionalpaymentmethodtype","abstract":[{"text":"The Type of Payment that is about to take place.","type":"text"}],"role":"symbol","title":"AdditionalPaymentMethodType","navigatorTitle":[{"kind":"identifier","text":"AdditionalPaymentMethodType"}],"kind":"symbol","identifier":"doc:\/\/com.squareup.MobilePaymentsSDKAPI\/documentation\/MobilePaymentsSDKAPI\/AdditionalPaymentMethodType","type":"topic","fragments":[{"kind":"keyword","text":"enum"},{"kind":"text","text":" "},{"kind":"identifier","text":"AdditionalPaymentMethodType"}]},"doc://com.squareup.MobilePaymentsSDKAPI/documentation/MobilePaymentsSDKAPI/ReaderConnectionFailureRecoverySuggestion":{"fragments":[{"kind":"keyword","text":"enum"},{"kind":"text","text":" "},{"kind":"identifier","text":"ReaderConnectionFailureRecoverySuggestion"}],"url":"\/documentation\/mobilepaymentssdkapi\/readerconnectionfailurerecoverysuggestion","navigatorTitle":[{"kind":"identifier","text":"ReaderConnectionFailureRecoverySuggestion"}],"role":"symbol","title":"ReaderConnectionFailureRecoverySuggestion","abstract":[{"type":"text","text":"Provides a suggestion for how to attempt to recover from a failed connection."}],"type":"topic","kind":"symbol","identifier":"doc:\/\/com.squareup.MobilePaymentsSDKAPI\/documentation\/MobilePaymentsSDKAPI\/ReaderConnectionFailureRecoverySuggestion"},"doc://com.squareup.MobilePaymentsSDKAPI/documentation/MobilePaymentsSDKAPI/PromptParameters":{"fragments":[{"kind":"keyword","text":"class"},{"kind":"text","text":" "},{"kind":"identifier","text":"PromptParameters"}],"abstract":[{"type":"text","text":"Parameters to describe the payment prompt for a single payment made using Mobile Payments SDK."}],"type":"topic","kind":"symbol","identifier":"doc:\/\/com.squareup.MobilePaymentsSDKAPI\/documentation\/MobilePaymentsSDKAPI\/PromptParameters","role":"symbol","title":"PromptParameters","url":"\/documentation\/mobilepaymentssdkapi\/promptparameters","navigatorTitle":[{"kind":"identifier","text":"PromptParameters"}]},"doc://com.squareup.MobilePaymentsSDKAPI/documentation/MobilePaymentsSDKAPI/OfflinePayment":{"kind":"symbol","type":"topic","fragments":[{"kind":"keyword","text":"protocol"},{"kind":"text","text":" "},{"text":"OfflinePayment","kind":"identifier"}],"url":"\/documentation\/mobilepaymentssdkapi\/offlinepayment","title":"OfflinePayment","abstract":[{"type":"text","text":"A representation of an offline payment"}],"role":"symbol","navigatorTitle":[{"text":"OfflinePayment","kind":"identifier"}],"identifier":"doc:\/\/com.squareup.MobilePaymentsSDKAPI\/documentation\/MobilePaymentsSDKAPI\/OfflinePayment"},"doc://com.squareup.MobilePaymentsSDKAPI/documentation/MobilePaymentsSDKAPI/AuthorizationError":{"kind":"symbol","url":"\/documentation\/mobilepaymentssdkapi\/authorizationerror","fragments":[{"text":"enum","kind":"keyword"},{"text":" ","kind":"text"},{"text":"AuthorizationError","kind":"identifier"}],"navigatorTitle":[{"text":"AuthorizationError","kind":"identifier"}],"role":"symbol","abstract":[{"text":"Errors that occur when authorization fails.","type":"text"}],"type":"topic","identifier":"doc:\/\/com.squareup.MobilePaymentsSDKAPI\/documentation\/MobilePaymentsSDKAPI\/AuthorizationError","title":"AuthorizationError"},"doc://com.squareup.MobilePaymentsSDKAPI/documentation/MobilePaymentsSDKAPI/CardPaymentStatus":{"identifier":"doc:\/\/com.squareup.MobilePaymentsSDKAPI\/documentation\/MobilePaymentsSDKAPI\/CardPaymentStatus","role":"symbol","fragments":[{"kind":"keyword","text":"enum"},{"kind":"text","text":" "},{"kind":"identifier","text":"CardPaymentStatus"}],"navigatorTitle":[{"kind":"identifier","text":"CardPaymentStatus"}],"url":"\/documentation\/mobilepaymentssdkapi\/cardpaymentstatus","abstract":[{"text":"The status of the card payment.","type":"text"}],"title":"CardPaymentStatus","kind":"symbol","type":"topic"},"doc://com.squareup.MobilePaymentsSDKAPI/documentation/MobilePaymentsSDKAPI/Currency":{"kind":"symbol","type":"topic","abstract":[{"type":"text","text":"Represents a currency"}],"identifier":"doc:\/\/com.squareup.MobilePaymentsSDKAPI\/documentation\/MobilePaymentsSDKAPI\/Currency","navigatorTitle":[{"text":"Currency","kind":"identifier"}],"role":"symbol","fragments":[{"text":"enum","kind":"keyword"},{"text":" ","kind":"text"},{"text":"Currency","kind":"identifier"}],"url":"\/documentation\/mobilepaymentssdkapi\/currency","title":"Currency"},"doc://com.squareup.MobilePaymentsSDKAPI/documentation/MobilePaymentsSDKAPI/OfflinePaymentQueue":{"navigatorTitle":[{"text":"OfflinePaymentQueue","kind":"identifier"}],"url":"\/documentation\/mobilepaymentssdkapi\/offlinepaymentqueue","fragments":[{"text":"protocol","kind":"keyword"},{"text":" ","kind":"text"},{"text":"OfflinePaymentQueue","kind":"identifier"}],"title":"OfflinePaymentQueue","abstract":[{"type":"text","text":"Mechanism to interact with payments taken while offline"}],"identifier":"doc:\/\/com.squareup.MobilePaymentsSDKAPI\/documentation\/MobilePaymentsSDKAPI\/OfflinePaymentQueue","type":"topic","kind":"symbol","role":"symbol"},"doc://com.squareup.MobilePaymentsSDKAPI/documentation/MobilePaymentsSDKAPI/ReadCardInfoError":{"type":"topic","navigatorTitle":[{"kind":"identifier","text":"ReadCardInfoError"}],"title":"ReadCardInfoError","kind":"symbol","fragments":[{"kind":"keyword","text":"enum"},{"kind":"text","text":" "},{"kind":"identifier","text":"ReadCardInfoError"}],"abstract":[],"url":"\/documentation\/mobilepaymentssdkapi\/readcardinfoerror","identifier":"doc:\/\/com.squareup.MobilePaymentsSDKAPI\/documentation\/MobilePaymentsSDKAPI\/ReadCardInfoError","role":"symbol"},"doc://com.squareup.MobilePaymentsSDKAPI/documentation/MobilePaymentsSDKAPI/DelayAction":{"title":"DelayAction","url":"\/documentation\/mobilepaymentssdkapi\/delayaction","fragments":[{"text":"enum","kind":"keyword"},{"text":" ","kind":"text"},{"text":"DelayAction","kind":"identifier"}],"role":"symbol","navigatorTitle":[{"text":"DelayAction","kind":"identifier"}],"abstract":[{"type":"text","text":"Defines the actions to be applied to the payment when the "},{"code":"delayDuration","type":"codeVoice"},{"type":"text","text":" has elapsed. The action must be CANCEL or COMPLETE."}],"type":"topic","kind":"symbol","identifier":"doc:\/\/com.squareup.MobilePaymentsSDKAPI\/documentation\/MobilePaymentsSDKAPI\/DelayAction"},"doc://com.squareup.MobilePaymentsSDKAPI/documentation/MobilePaymentsSDKAPI/ReaderConnectionFailureReason":{"navigatorTitle":[{"text":"ReaderConnectionFailureReason","kind":"identifier"}],"identifier":"doc:\/\/com.squareup.MobilePaymentsSDKAPI\/documentation\/MobilePaymentsSDKAPI\/ReaderConnectionFailureReason","title":"ReaderConnectionFailureReason","url":"\/documentation\/mobilepaymentssdkapi\/readerconnectionfailurereason","kind":"symbol","type":"topic","role":"symbol","abstract":[{"text":"Indicates why a reader might have failed to connect to Square.","type":"text"}],"fragments":[{"text":"enum","kind":"keyword"},{"text":" ","kind":"text"},{"text":"ReaderConnectionFailureReason","kind":"identifier"}]},"doc://com.squareup.MobilePaymentsSDKAPI/documentation/MobilePaymentsSDKAPI/PaymentStatus":{"abstract":[{"text":"The current status of the payment.","type":"text"}],"title":"PaymentStatus","url":"\/documentation\/mobilepaymentssdkapi\/paymentstatus","role":"symbol","type":"topic","kind":"symbol","fragments":[{"text":"enum","kind":"keyword"},{"text":" ","kind":"text"},{"text":"PaymentStatus","kind":"identifier"}],"identifier":"doc:\/\/com.squareup.MobilePaymentsSDKAPI\/documentation\/MobilePaymentsSDKAPI\/PaymentStatus","navigatorTitle":[{"text":"PaymentStatus","kind":"identifier"}]},"doc://com.squareup.MobilePaymentsSDKAPI/documentation/MobilePaymentsSDKAPI/AdditionalPaymentMethod":{"url":"\/documentation\/mobilepaymentssdkapi\/additionalpaymentmethod","kind":"symbol","fragments":[{"text":"protocol","kind":"keyword"},{"text":" ","kind":"text"},{"text":"AdditionalPaymentMethod","kind":"identifier"}],"abstract":[{"text":"The additional payment method that we are attempting to charge.","type":"text"}],"type":"topic","role":"symbol","navigatorTitle":[{"text":"AdditionalPaymentMethod","kind":"identifier"}],"title":"AdditionalPaymentMethod","identifier":"doc:\/\/com.squareup.MobilePaymentsSDKAPI\/documentation\/MobilePaymentsSDKAPI\/AdditionalPaymentMethod"},"doc://com.squareup.MobilePaymentsSDKAPI/documentation/MobilePaymentsSDKAPI/PairingHandle":{"fragments":[{"text":"protocol","kind":"keyword"},{"text":" ","kind":"text"},{"text":"PairingHandle","kind":"identifier"}],"role":"symbol","url":"\/documentation\/mobilepaymentssdkapi\/pairinghandle","kind":"symbol","type":"topic","title":"PairingHandle","abstract":[{"text":"Represents an ongoing pairing with Square Reader and provides a way to cancel it","type":"text"}],"navigatorTitle":[{"text":"PairingHandle","kind":"identifier"}],"identifier":"doc:\/\/com.squareup.MobilePaymentsSDKAPI\/documentation\/MobilePaymentsSDKAPI\/PairingHandle"},"doc://com.squareup.MobilePaymentsSDKAPI/documentation/MobilePaymentsSDKAPI/CardEntryMethod":{"url":"\/documentation\/mobilepaymentssdkapi\/cardentrymethod","kind":"symbol","title":"CardEntryMethod","fragments":[{"kind":"keyword","text":"enum"},{"kind":"text","text":" "},{"kind":"identifier","text":"CardEntryMethod"}],"navigatorTitle":[{"kind":"identifier","text":"CardEntryMethod"}],"abstract":[{"type":"text","text":"The entry method used to provide a card’s details."}],"role":"symbol","identifier":"doc:\/\/com.squareup.MobilePaymentsSDKAPI\/documentation\/MobilePaymentsSDKAPI\/CardEntryMethod","type":"topic"},"doc://com.squareup.MobilePaymentsSDKAPI/documentation/MobilePaymentsSDKAPI/PaymentParameters":{"kind":"symbol","navigatorTitle":[{"kind":"identifier","text":"PaymentParameters"}],"abstract":[{"text":"Parameters to describe a single payment made using Mobile Payments SDK.","type":"text"}],"identifier":"doc:\/\/com.squareup.MobilePaymentsSDKAPI\/documentation\/MobilePaymentsSDKAPI\/PaymentParameters","type":"topic","role":"symbol","fragments":[{"kind":"keyword","text":"class"},{"kind":"text","text":" "},{"kind":"identifier","text":"PaymentParameters"}],"title":"PaymentParameters","url":"\/documentation\/mobilepaymentssdkapi\/paymentparameters"},"doc://com.squareup.MobilePaymentsSDKAPI/documentation/MobilePaymentsSDKAPI/ReaderObserver":{"identifier":"doc:\/\/com.squareup.MobilePaymentsSDKAPI\/documentation\/MobilePaymentsSDKAPI\/ReaderObserver","kind":"symbol","fragments":[{"text":"protocol","kind":"keyword"},{"kind":"text","text":" "},{"kind":"identifier","text":"ReaderObserver"}],"navigatorTitle":[{"kind":"identifier","text":"ReaderObserver"}],"type":"topic","title":"ReaderObserver","abstract":[{"type":"text","text":"Callback invoked to notify the application of a change to a single card reader."}],"role":"symbol","url":"\/documentation\/mobilepaymentssdkapi\/readerobserver"},"doc://com.squareup.MobilePaymentsSDKAPI/documentation/MobilePaymentsSDKAPI/SDKSettings":{"navigatorTitle":[{"text":"SDKSettings","kind":"identifier"}],"type":"topic","url":"\/documentation\/mobilepaymentssdkapi\/sdksettings","kind":"symbol","abstract":[{"type":"text","text":"SDK-level settings containing general information about the Mobile Payments SDK."}],"role":"symbol","title":"SDKSettings","fragments":[{"text":"protocol","kind":"keyword"},{"text":" ","kind":"text"},{"text":"SDKSettings","kind":"identifier"}],"identifier":"doc:\/\/com.squareup.MobilePaymentsSDKAPI\/documentation\/MobilePaymentsSDKAPI\/SDKSettings"},"doc://com.squareup.MobilePaymentsSDKAPI/documentation/MobilePaymentsSDKAPI/TrackingConsentState":{"kind":"symbol","type":"topic","role":"symbol","abstract":[{"type":"text","text":"Tracks user consent for analytics and data collection."}],"fragments":[{"text":"enum","kind":"keyword"},{"text":" ","kind":"text"},{"text":"TrackingConsentState","kind":"identifier"}],"url":"\/documentation\/mobilepaymentssdkapi\/trackingconsentstate","identifier":"doc:\/\/com.squareup.MobilePaymentsSDKAPI\/documentation\/MobilePaymentsSDKAPI\/TrackingConsentState","title":"TrackingConsentState","navigatorTitle":[{"text":"TrackingConsentState","kind":"identifier"}]},"doc://com.squareup.MobilePaymentsSDKAPI/documentation/MobilePaymentsSDKAPI/CardInputMethods":{"fragments":[{"kind":"keyword","text":"class"},{"kind":"text","text":" "},{"kind":"identifier","text":"CardInputMethods"}],"identifier":"doc:\/\/com.squareup.MobilePaymentsSDKAPI\/documentation\/MobilePaymentsSDKAPI\/CardInputMethods","title":"CardInputMethods","type":"topic","kind":"symbol","navigatorTitle":[{"kind":"identifier","text":"CardInputMethods"}],"url":"\/documentation\/mobilepaymentssdkapi\/cardinputmethods","abstract":[{"type":"text","text":"Methods of payments that might be supported by readers"}],"role":"symbol"},"doc://com.squareup.MobilePaymentsSDKAPI/documentation/MobilePaymentsSDKAPI/SDKManager":{"identifier":"doc:\/\/com.squareup.MobilePaymentsSDKAPI\/documentation\/MobilePaymentsSDKAPI\/SDKManager","abstract":[{"type":"text","text":"Manages initialization and lifecycle for the Mobile Payments SDK."}],"role":"symbol","title":"SDKManager","kind":"symbol","fragments":[{"text":"protocol","kind":"keyword"},{"text":" ","kind":"text"},{"text":"SDKManager","kind":"identifier"}],"url":"\/documentation\/mobilepaymentssdkapi\/sdkmanager","navigatorTitle":[{"text":"SDKManager","kind":"identifier"}],"type":"topic"},"doc://com.squareup.MobilePaymentsSDKAPI/documentation/MobilePaymentsSDKAPI":{"abstract":[],"kind":"symbol","url":"\/documentation\/mobilepaymentssdkapi","title":"MobilePaymentsSDKAPI","role":"collection","identifier":"doc:\/\/com.squareup.MobilePaymentsSDKAPI\/documentation\/MobilePaymentsSDKAPI","type":"topic"},"doc://com.squareup.MobilePaymentsSDKAPI/documentation/MobilePaymentsSDKAPI/ReaderConnectionInfo":{"type":"topic","fragments":[{"kind":"keyword","text":"protocol"},{"kind":"text","text":" "},{"kind":"identifier","text":"ReaderConnectionInfo"}],"identifier":"doc:\/\/com.squareup.MobilePaymentsSDKAPI\/documentation\/MobilePaymentsSDKAPI\/ReaderConnectionInfo","url":"\/documentation\/mobilepaymentssdkapi\/readerconnectioninfo","title":"ReaderConnectionInfo","kind":"symbol","abstract":[{"type":"text","text":"Contains connection information about a Readers current state."}],"role":"symbol","navigatorTitle":[{"kind":"identifier","text":"ReaderConnectionInfo"}]},"doc://com.squareup.MobilePaymentsSDKAPI/documentation/MobilePaymentsSDKAPI/AuthorizationStateObserver":{"type":"topic","abstract":[{"text":"Observer for receiving updates when authorization state changes.","type":"text"}],"fragments":[{"kind":"keyword","text":"protocol"},{"kind":"text","text":" "},{"kind":"identifier","text":"AuthorizationStateObserver"}],"navigatorTitle":[{"kind":"identifier","text":"AuthorizationStateObserver"}],"title":"AuthorizationStateObserver","url":"\/documentation\/mobilepaymentssdkapi\/authorizationstateobserver","kind":"symbol","identifier":"doc:\/\/com.squareup.MobilePaymentsSDKAPI\/documentation\/MobilePaymentsSDKAPI\/AuthorizationStateObserver","role":"symbol"},"doc://com.squareup.MobilePaymentsSDKAPI/documentation/MobilePaymentsSDKAPI/TapToPaySettings":{"kind":"symbol","type":"topic","title":"TapToPaySettings","identifier":"doc:\/\/com.squareup.MobilePaymentsSDKAPI\/documentation\/MobilePaymentsSDKAPI\/TapToPaySettings","role":"symbol","abstract":[{"code":"TapToPaySettings","type":"codeVoice"},{"type":"text","text":" manages the usage of the Tap to Pay on iPhone reader."}],"fragments":[{"kind":"keyword","text":"protocol"},{"kind":"text","text":" "},{"kind":"identifier","text":"TapToPaySettings"}],"url":"\/documentation\/mobilepaymentssdkapi\/taptopaysettings","navigatorTitle":[{"kind":"identifier","text":"TapToPaySettings"}]},"doc://com.squareup.MobilePaymentsSDKAPI/documentation/MobilePaymentsSDKAPI/ReaderUnavailableReason":{"title":"ReaderUnavailableReason","identifier":"doc:\/\/com.squareup.MobilePaymentsSDKAPI\/documentation\/MobilePaymentsSDKAPI\/ReaderUnavailableReason","kind":"symbol","navigatorTitle":[{"text":"ReaderUnavailableReason","kind":"identifier"}],"url":"\/documentation\/mobilepaymentssdkapi\/readerunavailablereason","abstract":[{"text":"Indicates why a reader may be unavailable or unable to process payments.","type":"text"}],"type":"topic","role":"symbol","fragments":[{"text":"enum","kind":"keyword"},{"text":" ","kind":"text"},{"text":"ReaderUnavailableReason","kind":"identifier"}]},"doc://com.squareup.MobilePaymentsSDKAPI/documentation/MobilePaymentsSDKAPI/SettingsManager":{"url":"\/documentation\/mobilepaymentssdkapi\/settingsmanager","title":"SettingsManager","type":"topic","kind":"symbol","identifier":"doc:\/\/com.squareup.MobilePaymentsSDKAPI\/documentation\/MobilePaymentsSDKAPI\/SettingsManager","role":"symbol","navigatorTitle":[{"text":"SettingsManager","kind":"identifier"}],"fragments":[{"text":"protocol","kind":"keyword"},{"text":" ","kind":"text"},{"text":"SettingsManager","kind":"identifier"}],"abstract":[{"text":"The ","type":"text"},{"code":"SettingsManager","type":"codeVoice"},{"text":" manages presenting, retrieving, and updating SDK settings.","type":"text"}]},"doc://com.squareup.MobilePaymentsSDKAPI/documentation/MobilePaymentsSDKAPI/PaymentManager":{"identifier":"doc:\/\/com.squareup.MobilePaymentsSDKAPI\/documentation\/MobilePaymentsSDKAPI\/PaymentManager","url":"\/documentation\/mobilepaymentssdkapi\/paymentmanager","role":"symbol","kind":"symbol","navigatorTitle":[{"text":"PaymentManager","kind":"identifier"}],"abstract":[{"type":"text","text":"The "},{"type":"codeVoice","code":"PaymentManager"},{"type":"text","text":" handles creating a new payment."}],"type":"topic","title":"PaymentManager","fragments":[{"text":"protocol","kind":"keyword"},{"text":" ","kind":"text"},{"text":"PaymentManager","kind":"identifier"}]},"doc://com.squareup.MobilePaymentsSDKAPI/documentation/MobilePaymentsSDKAPI/AvailableCardInputMethodsObserver":{"url":"\/documentation\/mobilepaymentssdkapi\/availablecardinputmethodsobserver","identifier":"doc:\/\/com.squareup.MobilePaymentsSDKAPI\/documentation\/MobilePaymentsSDKAPI\/AvailableCardInputMethodsObserver","type":"topic","abstract":[{"type":"text","text":"Observer for receiving changes for the available card input methods."}],"navigatorTitle":[{"text":"AvailableCardInputMethodsObserver","kind":"identifier"}],"kind":"symbol","fragments":[{"text":"protocol","kind":"keyword"},{"text":" ","kind":"text"},{"text":"AvailableCardInputMethodsObserver","kind":"identifier"}],"role":"symbol","title":"AvailableCardInputMethodsObserver"},"doc://com.squareup.MobilePaymentsSDKAPI/documentation/MobilePaymentsSDKAPI/ReadCardInfoManager":{"navigatorTitle":[{"kind":"identifier","text":"ReadCardInfoManager"}],"fragments":[{"kind":"keyword","text":"protocol"},{"kind":"text","text":" "},{"kind":"identifier","text":"ReadCardInfoManager"}],"abstract":[{"text":"The ","type":"text"},{"code":"ReadCardInfoManager","type":"codeVoice"},{"text":" manages reading swiped or dipped cards without performing a payment.","type":"text"},{"text":" ","type":"text"},{"text":"This is useful for reading a cardholder name for autofilling forms, or to place on a receipt or ticket.","type":"text"}],"url":"\/documentation\/mobilepaymentssdkapi\/readcardinfomanager","type":"topic","kind":"symbol","identifier":"doc:\/\/com.squareup.MobilePaymentsSDKAPI\/documentation\/MobilePaymentsSDKAPI\/ReadCardInfoManager","role":"symbol","title":"ReadCardInfoManager"},"doc://com.squareup.MobilePaymentsSDKAPI/documentation/MobilePaymentsSDKAPI/PaymentSettings":{"url":"\/documentation\/mobilepaymentssdkapi\/paymentsettings","abstract":[{"type":"text","text":"Read-only settings that provide payment settings based on the current authenticated seller."}],"role":"symbol","kind":"symbol","fragments":[{"text":"protocol","kind":"keyword"},{"text":" ","kind":"text"},{"text":"PaymentSettings","kind":"identifier"}],"navigatorTitle":[{"text":"PaymentSettings","kind":"identifier"}],"type":"topic","identifier":"doc:\/\/com.squareup.MobilePaymentsSDKAPI\/documentation\/MobilePaymentsSDKAPI\/PaymentSettings","title":"PaymentSettings"},"doc://com.squareup.MobilePaymentsSDKAPI/documentation/MobilePaymentsSDKAPI/TapToPayPaymentSource":{"fragments":[{"kind":"keyword","text":"class"},{"kind":"text","text":" "},{"kind":"identifier","text":"TapToPayPaymentSource"}],"url":"\/documentation\/mobilepaymentssdkapi\/taptopaypaymentsource","identifier":"doc:\/\/com.squareup.MobilePaymentsSDKAPI\/documentation\/MobilePaymentsSDKAPI\/TapToPayPaymentSource","role":"symbol","navigatorTitle":[{"kind":"identifier","text":"TapToPayPaymentSource"}],"kind":"symbol","title":"TapToPayPaymentSource","abstract":[{"text":"Instructs the SDK to begin an Apple Tap to Pay Payment","type":"text"}],"type":"topic"},"doc://com.squareup.MobilePaymentsSDKAPI/documentation/MobilePaymentsSDKAPI/ReaderStatusInfo":{"kind":"symbol","role":"symbol","fragments":[{"text":"protocol","kind":"keyword"},{"text":" ","kind":"text"},{"text":"ReaderStatusInfo","kind":"identifier"}],"navigatorTitle":[{"text":"ReaderStatusInfo","kind":"identifier"}],"url":"\/documentation\/mobilepaymentssdkapi\/readerstatusinfo","identifier":"doc:\/\/com.squareup.MobilePaymentsSDKAPI\/documentation\/MobilePaymentsSDKAPI\/ReaderStatusInfo","type":"topic","abstract":[],"title":"ReaderStatusInfo"},"doc://com.squareup.MobilePaymentsSDKAPI/documentation/MobilePaymentsSDKAPI/AdditionalPaymentMethods":{"abstract":[{"type":"text","text":"Additional payment methods supported by MobilePaymentsSDK"}],"identifier":"doc:\/\/com.squareup.MobilePaymentsSDKAPI\/documentation\/MobilePaymentsSDKAPI\/AdditionalPaymentMethods","role":"symbol","title":"AdditionalPaymentMethods","kind":"symbol","type":"topic","fragments":[{"kind":"keyword","text":"class"},{"kind":"text","text":" "},{"kind":"identifier","text":"AdditionalPaymentMethods"}],"navigatorTitle":[{"kind":"identifier","text":"AdditionalPaymentMethods"}],"url":"\/documentation\/mobilepaymentssdkapi\/additionalpaymentmethods"}}}